{
  "id": "pf1e-spell-points",
  "title": "Pathfinder 1e - Spell Points",
  "version": "1.0.0",
  "compatibility": {
    "minimum": "11",
    "verified": "11"
  },
  "relationships": {
    "systems": [
      {
        "id": "pf1",
        "type": "system",
        "manifest": "https://gitlab.com/foundryvtt_pathfinder1e/foundryvtt-pathfinder1/-/releases/permalink/latest/downloads/system.json",
        "compatibility": {
          "minimum": "9.6",
          "verified": "9.7"
        }
      }
    ]
  },
  "description": "Improve Spell Point support for Pathfinder 1e.",
  "authors": [
    {
      "name": "KitCat",
      "email": "katsulynx@gmail.com",
      "discord": "kitcat"
    }
  ],
  "esmodules": [
    "modules/pf1e-spellPoints-main.mjs"
  ],
  "styles": [
    "styles/pf1e-spellPoints.css"
  ],
  "languages": [
    {
      "lang": "en",
      "name": "English",
      "path": "lang/en.json"
    },
    {
      "lang": "de",
      "name": "Deutsch (German)",
      "path": "lang/de.json"
    }
  ],
  "readme": "README.md",
  "license": "LICENSE",
  "bugs": "https://github.com/KitCat420/pf1e-spell-points/issues",
  "url": "#{URL}#",
  "manifest": "#{MANIFEST}#",
  "download": "#{DOWNLOAD}#"
}